snyksh.py
snyksh-0.1.1.dist-info/entry_points.txt
snyksh-0.1.1.dist-info/LICENSE
snyksh-0.1.1.dist-info/WHEEL
snyksh-0.1.1.dist-info/METADATA
snyksh-0.1.1.dist-info/RECORD
