Metadata-Version: 2.1
Name: snyksh
Version: 0.1.1
Summary: An interactive shell interface for the Snyk API
Home-page: https://github.com/garethr/snyksh
License: MIT
Author: Gareth Rushgrove
Author-email: gareth@morethanseven.net
Requires-Python: >=3.7,<4.0
Classifier: License :: OSI Approved :: MIT License
Classifier: Programming Language :: Python :: 3
Classifier: Programming Language :: Python :: 3.7
Requires-Dist: ipython
Requires-Dist: prettyprinter
Requires-Dist: pysnyk
Requires-Dist: termcolor
Project-URL: Repository, https://github.com/garethr/snyksh
